crisp_py/__init__.py
crisp_py/camera/__init__.py
crisp_py/camera/camera.py
crisp_py/camera/camera_config.py
crisp_py/config/__init__.py
crisp_py/config/path.py
crisp_py/config/cameras/right_wrist_camera.yaml
crisp_py/config/cameras/third_person_camera.yaml
crisp_py/config/cameras/wrist_camera.yaml
crisp_py/config/control/clipped_cartesian_impedance.yaml
crisp_py/config/control/default_cartesian_impedance.yaml
crisp_py/config/control/default_operational_space_controller.yaml
crisp_py/config/control/gravity_compensation.yaml
crisp_py/config/control/gravity_compensation_on_plane.yaml
crisp_py/config/control/joint_control.yaml
crisp_py/config/control/joint_velocity_control.yaml
crisp_py/config/control/no_friction_cartesian_impedance.yaml
crisp_py/config/grippers/aloha-gripper.yaml
crisp_py/config/grippers/gripper_franka.yaml
crisp_py/config/grippers/gripper_left.yaml
crisp_py/config/grippers/gripper_left_config.yaml
crisp_py/config/grippers/gripper_right.yaml
crisp_py/config/grippers/gripper_right_config.yaml
crisp_py/config/grippers/gripper_uncalibrated.yaml
crisp_py/config/grippers/gripper_with_trigger.yaml
crisp_py/config/grippers/trigger_left.yaml
crisp_py/config/robots/fr3.yaml
crisp_py/config/robots/fr3_left.yaml
crisp_py/config/robots/fr3_right.yaml
crisp_py/config/robots/panda.yaml
crisp_py/config/sensors/anyskin_sensor.yaml
crisp_py/config/sensors/force_torque_sensor.yaml
crisp_py/config/sensors/mock_force_torque_sensor.yaml
crisp_py/control/__init__.py
crisp_py/control/controller_switcher.py
crisp_py/control/joint_trajectory_controller_client.py
crisp_py/control/parameters_client.py
crisp_py/gripper/__init__.py
crisp_py/gripper/gripper.py
crisp_py/gripper/gripper_config.py
crisp_py/robot/__init__.py
crisp_py/robot/robot.py
crisp_py/robot/robot_config.py
crisp_py/sensors/__init__.py
crisp_py/sensors/float32_array_sensor.py
crisp_py/sensors/force_torque_sensor.py
crisp_py/sensors/sensor.py
crisp_py/sensors/sensor_config.py
crisp_py/utils/__init__.py
crisp_python-3.1.0.dist-info/licenses/LICENSE.md
crisp_python-3.1.0.dist-info/METADATA
crisp_python-3.1.0.dist-info/WHEEL
crisp_python-3.1.0.dist-info/top_level.txt
crisp_python-3.1.0.dist-info/RECORD
