Metadata-Version: 2.4
Name: crisp-python
Version: 3.1.0
Summary: Simple python interface to control robots that use crisp_controllers and other ROS2 components.
Project-URL: Homepage, https://utiasDSL.github.io/crisp_controllers/
Requires-Python: >=3.11
License-File: LICENSE.md
Requires-Dist: scipy
Requires-Dist: numpy<=2.3
Dynamic: license-file
